{
    "CA CALENDAR": null,
    "CH ANLA": {
        "displayProperty": [],
        "requestedFields": [],
        "selection": [],
        "text": "Asset Master Record Segment",
        "valueProperty": [
            "BUKRS",
            "ANLN1",
            "ANLN2"
        ]
    },
    "CH ANLH": {
        "displayProperty": [],
        "requestedFields": [],
        "selection": [],
        "text": "Main asset number",
        "valueProperty": [
            "BUKRS",
            "ANLN1"
        ]
    },
    "CH AUFK": {
        "displayProperty": [],
        "requestedFields": [],
        "selection": [],
        "text": "Order master data",
        "valueProperty": [
            "AUFNR"
        ]
    },
    "CH AUKO": {
        "displayProperty": [],
        "requestedFields": [],
        "selection": [],
        "text": "Allocation Table Document Header",
        "valueProperty": [
            "ABELN"
        ]
    },
    "CH AUPO": {
        "displayProperty": [],
        "requestedFields": [],
        "selection": [],
        "text": "Allocation Table Document Item",
        "valueProperty": [
            "ABELN",
            "ABELP"
        ]
    },
    "CH BALHDR": {
        "displayProperty": [],
        "requestedFields": [],
        "selection": [],
        "text": "Application log: log header",
        "valueProperty": [
            "LOGNUMBER"
        ]
    },
    "CH BALM": {
        "displayProperty": [],
        "requestedFields": [],
        "selection": [],
        "text": "Application log: log message",
        "valueProperty": [
            "LOGNUMBER",
            "MSGNUMBER"
        ]
    },
    "CH CKPH": {
        "displayProperty": [],
        "requestedFields": [],
        "selection": [],
        "text": "Master Record: Cost Object ID Number",
        "valueProperty": [
            "KSTRG",
            "DATBI"
        ]
    },
    "CH EBAN": {
        "displayProperty": [],
        "requestedFields": [],
        "selection": [],
        "text": "Purchase Requisition",
        "valueProperty": [
            "BANFN",
            "BNFPO"
        ]
    },
    "CH EIKP": {
        "displayProperty": [],
        "requestedFields": [],
        "selection": [],
        "text": "Foreign Trade: Export/Import Header Data",
        "valueProperty": [
            "EXNUM"
        ]
    },
    "CH EINA": {
        "displayProperty": [],
        "requestedFields": [],
        "selection": [],
        "text": "Purchasing Info Record: General Data",
        "valueProperty": [
            "INFNR"
        ]
    },
    "CH EKET": {
        "displayProperty": [],
        "requestedFields": [],
        "selection": [],
        "text": "Scheduling Agreement Schedule Lines",
        "valueProperty": [
            "EBELN",
            "EBELP",
            "ETENR"
        ]
    },
    "CH EKKO": {
        "displayProperty": [],
        "requestedFields": [],
        "selection": [],
        "text": "Purchasing Document Header",
        "valueProperty": [
            "EBELN"
        ]
    },
    "CH EKPO": {
        "displayProperty": [],
        "requestedFields": [],
        "selection": [],
        "text": "Purchasing Document Item",
        "valueProperty": [
            "EBELN",
            "EBELP"
        ]
    },
    "CH ESLA": {
        "displayProperty": [],
        "requestedFields": [],
        "selection": [],
        "text": "Service Type Editions",
        "valueProperty": [
            "LBNUM",
            "AUSGB"
        ]
    },
    "CH ESLH": {
        "displayProperty": [],
        "requestedFields": [],
        "selection": [],
        "text": "Service Package Header Data",
        "valueProperty": [
            "PACKNO"
        ]
    },
    "CH MCH1": {
        "displayProperty": [],
        "requestedFields": [],
        "selection": [],
        "text": "Batches (if Batch Management Cross-Plant)",
        "valueProperty": [
            "MATNR",
            "CHARG"
        ]
    },
    "CH RESB": {
        "displayProperty": [],
        "requestedFields": [],
        "selection": [],
        "text": "Reservation/dependent requirements",
        "valueProperty": [
            "RSNUM",
            "RSPOS",
            "RSART"
        ]
    },
    "CH VBEP": {
        "displayProperty": [],
        "requestedFields": [],
        "selection": [],
        "text": "Sales Document: Schedule Line Data",
        "valueProperty": [
            "VBELN",
            "POSNR",
            "ETENR"
        ]
    },
    "CH VBUK": {
        "displayProperty": [],
        "requestedFields": [],
        "selection": [],
        "text": "Sales Document: Header Status and Administrative Data",
        "valueProperty": [
            "VBELN"
        ]
    },
    "CH VBUP": {
        "displayProperty": [],
        "requestedFields": [],
        "selection": [],
        "text": "Sales Document: Item Status",
        "valueProperty": [
            "VBELN",
            "POSNR"
        ]
    },
    "CL CLOCK": null,
    "CT ADRC": {
        "displayProperty": [],
        "requestedFields": [],
        "selection": [],
        "text": "Addresses (Business Address Services)",
        "valueProperty": [
            "ADDRNUMBER",
            "DATE_FROM",
            "NATION"
        ]
    },
    "CT ADRREGGRP": {
        "displayProperty": [],
        "requestedFields": [],
        "selection": [],
        "text": "Regional structure grouping",
        "valueProperty": [
            "REGIOGROUP"
        ]
    },
    "CT ADRSTRTYPE": {
        "displayProperty": [],
        "requestedFields": [],
        "selection": [],
        "text": "Street type",
        "valueProperty": [
            "COUNTRY",
            "STRTYPEAB"
        ]
    },
    "CT ANLA": {
        "displayProperty": [],
        "requestedFields": [],
        "selection": [],
        "text": "Asset Master Record Segment",
        "valueProperty": [
            "BUKRS",
            "ANLN1",
            "ANLN2"
        ]
    },
    "CT ANLH": {
        "displayProperty": [],
        "requestedFields": [],
        "selection": [],
        "text": "Main asset number",
        "valueProperty": [
            "BUKRS",
            "ANLN1"
        ]
    },
    "CT AUFK": {
        "displayProperty": [],
        "requestedFields": [],
        "selection": [],
        "text": "Order master data",
        "valueProperty": [
            "AUFNR"
        ]
    },
    "CT CEPC": {
        "displayProperty": [],
        "requestedFields": [],
        "selection": [],
        "text": "Profit Center Master Data Table",
        "valueProperty": [
            "PRCTR",
            "DATBI",
            "KOKRS"
        ]
    },
    "CT CKPH": {
        "displayProperty": [],
        "requestedFields": [],
        "selection": [],
        "text": "Master Record: Cost Object ID Number",
        "valueProperty": [
            "KSTRG",
            "DATBI"
        ]
    },
    "CT CSKS": {
        "displayProperty": [],
        "requestedFields": [],
        "selection": [],
        "text": "Cost Center Master Record",
        "valueProperty": [
            "KOKRS",
            "KOSTL",
            "DATBI"
        ]
    },
    "CT DD02L": {
        "displayProperty": [],
        "requestedFields": [],
        "selection": [],
        "text": "SAP Tables",
        "valueProperty": [
            "TABNAME",
            "AS4LOCAL",
            "AS4VERS"
        ]
    },
    "CT EBAN": {
        "displayProperty": [],
        "requestedFields": [],
        "selection": [],
        "text": "Purchase Requisition",
        "valueProperty": [
            "BANFN",
            "BNFPO"
        ]
    },
    "CT EKPO": {
        "displayProperty": [],
        "requestedFields": [],
        "selection": [],
        "text": "Purchasing Document Item",
        "valueProperty": [
            "EBELN",
            "EBELP"
        ]
    },
    "CT ESLH": {
        "displayProperty": [],
        "requestedFields": [],
        "selection": [],
        "text": "Service Package Header Data",
        "valueProperty": [
            "PACKNO"
        ]
    },
    "CT FMCI": {
        "displayProperty": [],
        "requestedFields": [],
        "selection": [],
        "text": "Commitment items master data",
        "valueProperty": [
            "FIKRS",
            "GJAHR",
            "FIPEX"
        ]
    },
    "CT FMFCTR": {
        "displayProperty": [],
        "requestedFields": [],
        "selection": [],
        "text": "Funds Center Master Record",
        "valueProperty": [
            "FIKRS",
            "FICTR",
            "DATBIS"
        ]
    },
    "CT FMFINCODE": {
        "displayProperty": [],
        "requestedFields": [],
        "selection": [],
        "text": "FIFM: Financing code",
        "valueProperty": [
            "FIKRS",
            "FINCODE"
        ]
    },
    "CT FMFUNDBPD": {
        "displayProperty": [],
        "requestedFields": [],
        "selection": [],
        "text": "FM: Assignments of Funds to Budget Periods",
        "valueProperty": [
            "FIKRS",
            "FINCODE",
            "BUDGET_PD"
        ]
    },
    "CT FMFXPO": {
        "displayProperty": [],
        "requestedFields": [],
        "selection": [],
        "text": "Commitment item, internal and external number (conversion)",
        "valueProperty": [
            "FIPOS"
        ]
    },
    "CT KBLK": {
        "displayProperty": [],
        "requestedFields": [],
        "selection": [],
        "text": "Document Header: Manual Document Entry",
        "valueProperty": [
            "BELNR"
        ]
    },
    "CT KBLP": {
        "displayProperty": [],
        "requestedFields": [],
        "selection": [],
        "text": "Document Item: Manual Document Entry",
        "valueProperty": [
            "BELNR",
            "BLPOS"
        ]
    },
    "CT KNA1": {
        "displayProperty": [],
        "requestedFields": [],
        "selection": [],
        "text": "General Data in Customer Master",
        "valueProperty": [
            "KUNNR"
        ]
    },
    "CT LFA1": {
        "displayProperty": [],
        "requestedFields": [],
        "selection": [],
        "text": "Vendor Master (General Section)",
        "valueProperty": [
            "LIFNR"
        ]
    },
    "CT MARA": {
        "displayProperty": [],
        "requestedFields": [],
        "selection": [],
        "text": "General Material Data",
        "valueProperty": [
            "MATNR"
        ]
    },
    "CT MCH1": {
        "displayProperty": [],
        "requestedFields": [],
        "selection": [],
        "text": "Batches (if Batch Management Cross-Plant)",
        "valueProperty": [
            "MATNR",
            "CHARG"
        ]
    },
    "CT T005": {
        "displayProperty": [],
        "requestedFields": [],
        "selection": [],
        "text": "Countries",
        "valueProperty": [
            "LAND1"
        ]
    },
    "CT T005S": {
        "displayProperty": [],
        "requestedFields": [],
        "selection": [],
        "text": "Taxes: Region (Province) Key",
        "valueProperty": [
            "LAND1",
            "BLAND"
        ]
    },
    "CT T007A": {
        "displayProperty": [],
        "requestedFields": [],
        "selection": [],
        "text": "Tax Keys",
        "valueProperty": [
            "KALSM",
            "MWSKZ"
        ]
    },
    "CT T027A": {
        "displayProperty": [],
        "requestedFields": [],
        "selection": [],
        "text": "Shipping Instructions, Purchasing",
        "valueProperty": [
            "EVERS"
        ]
    },
    "CT T149D": {
        "displayProperty": [],
        "requestedFields": [],
        "selection": [],
        "text": "Global Valuation Types",
        "valueProperty": [
            "BWTAR"
        ]
    },
    "CT T161": {
        "displayProperty": [],
        "requestedFields": [],
        "selection": [],
        "text": "Purchasing Document Types",
        "valueProperty": [
            "BSTYP",
            "BSART"
        ]
    },
    "CT T161E": {
        "displayProperty": [],
        "requestedFields": [],
        "selection": [],
        "text": "Release Codes",
        "valueProperty": [
            "FRGAB"
        ]
    },
    "CT T163E": {
        "displayProperty": [],
        "requestedFields": [],
        "selection": [],
        "text": "Confirmation Categories",
        "valueProperty": [
            "EBTYP"
        ]
    },
    "CT T163L": {
        "displayProperty": [],
        "requestedFields": [],
        "selection": [],
        "text": "Confirmation Control Keys",
        "valueProperty": [
            "BSTAE"
        ]
    },
    "CT T167F": {
        "displayProperty": [],
        "requestedFields": [],
        "selection": [],
        "text": "Formulas for Service Lines",
        "valueProperty": [
            "FORMELNR"
        ]
    },
    "CT T16FB": {
        "displayProperty": [],
        "requestedFields": [],
        "selection": [],
        "text": "Release Indicator: Purchasing Document",
        "valueProperty": [
            "FRGKE"
        ]
    },
    "CT T16FC": {
        "displayProperty": [],
        "requestedFields": [],
        "selection": [],
        "text": "Release Codes",
        "valueProperty": [
            "FRGGR",
            "FRGCO"
        ]
    },
    "CT T16FG": {
        "displayProperty": [],
        "requestedFields": [],
        "selection": [],
        "text": "Release Groups",
        "valueProperty": [
            "FRGGR"
        ]
    },
    "CT T16FS": {
        "displayProperty": [],
        "requestedFields": [],
        "selection": [],
        "text": "Release Strategies",
        "valueProperty": [
            "FRGGR",
            "FRGSX"
        ]
    },
    "CT T512W": {
        "displayProperty": [],
        "requestedFields": [],
        "selection": [],
        "text": "Wage Type Valuation",
        "valueProperty": [
            "MOLGA",
            "LGART",
            "ENDDA"
        ]
    },
    "CT T615": {
        "displayProperty": [],
        "requestedFields": [],
        "selection": [],
        "text": "Foreign Trade: Customs Offices",
        "valueProperty": [
            "LAND1",
            "ZOLLA"
        ]
    },
    "CT T618": {
        "displayProperty": [],
        "requestedFields": [],
        "selection": [],
        "text": "Foreign Trade: Modes of Transport",
        "valueProperty": [
            "LAND1",
            "EXPVZ"
        ]
    },
    "CT T683": {
        "displayProperty": [],
        "requestedFields": [],
        "selection": [],
        "text": "Pricing procedures",
        "valueProperty": [
            "KVEWE",
            "KAPPL",
            "KALSM"
        ]
    },
    "CT T6WSP": {
        "displayProperty": [],
        "requestedFields": [],
        "selection": [],
        "text": "Check Table for Season Indicator",
        "valueProperty": [
            "SAISO"
        ]
    },
    "CT T8JJ": {
        "displayProperty": [],
        "requestedFields": [],
        "selection": [],
        "text": "Recovery Indicator",
        "valueProperty": [
            "BUKRS",
            "RECID"
        ]
    },
    "CT TBDLS": {
        "displayProperty": [],
        "requestedFields": [],
        "selection": [],
        "text": "Logical system",
        "valueProperty": [
            "LOGSYS"
        ]
    },
    "CT TCURC": {
        "displayProperty": [],
        "requestedFields": [],
        "selection": [],
        "text": "Currency Codes",
        "valueProperty": [
            "WAERS"
        ]
    },
    "CT TFKB": {
        "displayProperty": [],
        "requestedFields": [],
        "selection": [],
        "text": "Functional areas",
        "valueProperty": [
            "FKBER"
        ]
    },
    "CT TGSB": {
        "displayProperty": [],
        "requestedFields": [],
        "selection": [],
        "text": "Business Areas",
        "valueProperty": [
            "GSBER"
        ]
    },
    "CT TKA01": {
        "displayProperty": [],
        "requestedFields": [],
        "selection": [],
        "text": "Controlling Areas",
        "valueProperty": [
            "KOKRS"
        ]
    },
    "CT TMAM": {
        "displayProperty": [],
        "requestedFields": [],
        "selection": [],
        "text": "Internal Comment on Quotation",
        "valueProperty": [
            "AGMEM"
        ]
    },
    "CT TMFG": {
        "displayProperty": [],
        "requestedFields": [],
        "selection": [],
        "text": "Material freight groups",
        "valueProperty": [
            "MFRGR"
        ]
    },
    "CT TMPPF": {
        "displayProperty": [],
        "requestedFields": [],
        "selection": [],
        "text": "Control Profile for Manufacturer Part Number Management",
        "valueProperty": [
            "MPROF"
        ]
    },
    "CT TMSI1": {
        "displayProperty": [],
        "requestedFields": [],
        "selection": [],
        "text": "Sub-Item Category in Purchasing",
        "valueProperty": [
            "UPTYP"
        ]
    },
    "CT TMSI2": {
        "displayProperty": [],
        "requestedFields": [],
        "selection": [],
        "text": "Processing Key for Sub-Items",
        "valueProperty": [
            "SIKGR"
        ]
    },
    "CT TMW3T": {
        "displayProperty": [],
        "requestedFields": [],
        "selection": [],
        "text": "Entity Table: Catalogs",
        "valueProperty": [
            "KATALOG"
        ]
    },
    "CT TSAC": {
        "displayProperty": [],
        "requestedFields": [],
        "selection": [],
        "text": "Communication Methods (Business Address Services)",
        "valueProperty": [
            "COMM_TYPE"
        ]
    },
    "CT TSAD3": {
        "displayProperty": [],
        "requestedFields": [],
        "selection": [],
        "text": "Forms of Address (Key) (Business Address Services)",
        "valueProperty": [
            "TITLE"
        ]
    },
    "CT TSAD6": {
        "displayProperty": [],
        "requestedFields": [],
        "selection": [],
        "text": "Source Address or Personal Data (Business Address Services)",
        "valueProperty": [
            "ORIGIN"
        ]
    },
    "CT TSADV": {
        "displayProperty": [],
        "requestedFields": [],
        "selection": [],
        "text": "International versions of addresses",
        "valueProperty": [
            "NATION"
        ]
    },
    "CT TTXID": {
        "displayProperty": [],
        "requestedFields": [],
        "selection": [],
        "text": "Valid text IDs",
        "valueProperty": [
            "TDOBJECT",
            "TDID"
        ]
    },
    "CT TTXJ": {
        "displayProperty": [],
        "requestedFields": [],
        "selection": [],
        "text": "Check Table for Tax Jurisdiction",
        "valueProperty": [
            "KALSM",
            "TXJCD"
        ]
    },
    "CT TZONE": {
        "displayProperty": [],
        "requestedFields": [],
        "selection": [],
        "text": "Customers: Regional zones",
        "valueProperty": [
            "LAND1",
            "ZONE1"
        ]
    },
    "CT VBEP": {
        "displayProperty": [],
        "requestedFields": [],
        "selection": [],
        "text": "Sales Document: Schedule Line Data",
        "valueProperty": [
            "VBELN",
            "POSNR",
            "ETENR"
        ]
    },
    "CT VBUK": {
        "displayProperty": [],
        "requestedFields": [],
        "selection": [],
        "text": "Sales Document: Header Status and Administrative Data",
        "valueProperty": [
            "VBELN"
        ]
    },
    "CT VBUP": {
        "displayProperty": [],
        "requestedFields": [],
        "selection": [],
        "text": "Sales Document: Item Status",
        "valueProperty": [
            "VBELN",
            "POSNR"
        ]
    },
    "CT WAKH": {
        "displayProperty": [],
        "requestedFields": [],
        "selection": [],
        "text": "Promotion Header Data, IS-R",
        "valueProperty": [
            "AKTNR"
        ]
    },
    "CT WYT1": {
        "displayProperty": [],
        "requestedFields": [],
        "selection": [],
        "text": "Vendor Subrange",
        "valueProperty": [
            "LIFNR",
            "LTSNR"
        ]
    },
    "FV AD_CHECKST": [
        {
            "APPVAL": "",
            "DDLANGUAGE": "E",
            "DDTEXT": "Not Checked",
            "DOMNAME": "AD_CHECKST",
            "DOMVALUE_H": "",
            "DOMVALUE_L": "",
            "DOMVAL_HD": "",
            "DOMVAL_LD": "",
            "VALPOS": "0001"
        },
        {
            "APPVAL": "",
            "DDLANGUAGE": "E",
            "DDTEXT": "checked against city index",
            "DOMNAME": "AD_CHECKST",
            "DOMVALUE_H": "",
            "DOMVALUE_L": "C",
            "DOMVAL_HD": "",
            "DOMVAL_LD": "",
            "VALPOS": "0002"
        },
        {
            "APPVAL": "",
            "DDLANGUAGE": "E",
            "DDTEXT": "differs from city index",
            "DOMNAME": "AD_CHECKST",
            "DOMVALUE_H": "",
            "DOMVALUE_L": "D",
            "DOMVAL_HD": "",
            "DOMVAL_LD": "",
            "VALPOS": "0003"
        }
    ],
    "FV ASTAT": [
        {
            "APPVAL": "",
            "DDLANGUAGE": "E",
            "DDTEXT": "No Quotation Exists/Not Created via Sales",
            "DOMNAME": "ASTAT",
            "DOMVALUE_H": "",
            "DOMVALUE_L": "",
            "DOMVAL_HD": "",
            "DOMVAL_LD": "",
            "VALPOS": "0001"
        },
        {
            "APPVAL": "",
            "DDLANGUAGE": "E",
            "DDTEXT": "Quotation Exists in Case of RFQ Item",
            "DOMNAME": "ASTAT",
            "DOMVALUE_H": "",
            "DOMVALUE_L": "A",
            "DOMVAL_HD": "",
            "DOMVAL_LD": "",
            "VALPOS": "0002"
        },
        {
            "APPVAL": "",
            "DDLANGUAGE": "E",
            "DDTEXT": "Created via Production Order",
            "DOMNAME": "ASTAT",
            "DOMVALUE_H": "",
            "DOMVALUE_L": "F",
            "DOMVAL_HD": "",
            "DOMVAL_LD": "",
            "VALPOS": "0003"
        },
        {
            "APPVAL": "",
            "DDLANGUAGE": "E",
            "DDTEXT": "Created via Sales document",
            "DOMNAME": "ASTAT",
            "DOMVALUE_H": "",
            "DOMVALUE_L": "V",
            "DOMVAL_HD": "",
            "DOMVAL_LD": "",
            "VALPOS": "0004"
        },
        {
            "APPVAL": "",
            "DDLANGUAGE": "E",
            "DDTEXT": "Created via Allocation Table",
            "DOMNAME": "ASTAT",
            "DOMVALUE_H": "",
            "DOMVALUE_L": "W",
            "DOMVAL_HD": "",
            "DOMVAL_LD": "",
            "VALPOS": "0005"
        }
    ],
    "FV ATTYP": [
        {
            "APPVAL": "",
            "DDLANGUAGE": "E",
            "DDTEXT": "Single material (industry)",
            "DOMNAME": "ATTYP",
            "DOMVALUE_H": "",
            "DOMVALUE_L": "",
            "DOMVAL_HD": "",
            "DOMVAL_LD": "",
            "VALPOS": "0001"
        },
        {
            "APPVAL": "",
            "DDLANGUAGE": "E",
            "DDTEXT": "Single material",
            "DOMNAME": "ATTYP",
            "DOMVALUE_H": "",
            "DOMVALUE_L": "00",
            "DOMVAL_HD": "",
            "DOMVAL_LD": "",
            "VALPOS": "0002"
        },
        {
            "APPVAL": "",
            "DDLANGUAGE": "E",
            "DDTEXT": "Generic material",
            "DOMNAME": "ATTYP",
            "DOMVALUE_H": "",
            "DOMVALUE_L": "01",
            "DOMVAL_HD": "",
            "DOMVAL_LD": "",
            "VALPOS": "0003"
        },
        {
            "APPVAL": "",
            "DDLANGUAGE": "E",
            "DDTEXT": "Variant",
            "DOMNAME": "ATTYP",
            "DOMVALUE_H": "",
            "DOMVALUE_L": "02",
            "DOMVAL_HD": "",
            "DOMVAL_LD": "",
            "VALPOS": "0004"
        },
        {
            "APPVAL": "",
            "DDLANGUAGE": "E",
            "DDTEXT": "Sales set",
            "DOMNAME": "ATTYP",
            "DOMVALUE_H": "",
            "DOMVALUE_L": "10",
            "DOMVAL_HD": "",
            "DOMVAL_LD": "",
            "VALPOS": "0005"
        },
        {
            "APPVAL": "",
            "DDLANGUAGE": "E",
            "DDTEXT": "Prepack",
            "DOMNAME": "ATTYP",
            "DOMVALUE_H": "",
            "DOMVALUE_L": "11",
            "DOMVAL_HD": "",
            "DOMVAL_LD": "",
            "VALPOS": "0006"
        },
        {
            "APPVAL": "",
            "DDLANGUAGE": "E",
            "DDTEXT": "Display",
            "DOMNAME": "ATTYP",
            "DOMVALUE_H": "",
            "DOMVALUE_L": "12",
            "DOMVAL_HD": "",
            "DOMVAL_LD": "",
            "VALPOS": "0007"
        },
        {
            "APPVAL": "",
            "DDLANGUAGE": "E",
            "DDTEXT": "Material group material",
            "DOMNAME": "ATTYP",
            "DOMVALUE_H": "",
            "DOMVALUE_L": "20",
            "DOMVAL_HD": "",
            "DOMVAL_LD": "",
            "VALPOS": "0008"
        },
        {
            "APPVAL": "",
            "DDLANGUAGE": "E",
            "DDTEXT": "Hierarchy material",
            "DOMNAME": "ATTYP",
            "DOMVALUE_H": "",
            "DOMVALUE_L": "21",
            "DOMVAL_HD": "",
            "DOMVAL_LD": "",
            "VALPOS": "0009"
        },
        {
            "APPVAL": "",
            "DDLANGUAGE": "E",
            "DDTEXT": "Group material",
            "DOMNAME": "ATTYP",
            "DOMVALUE_H": "",
            "DOMVALUE_L": "22",
            "DOMVAL_HD": "",
            "DOMVAL_LD": "",
            "VALPOS": "0010"
        },
        {
            "APPVAL": "",
            "DDLANGUAGE": "E",
            "DDTEXT": "Material group reference material",
            "DOMNAME": "ATTYP",
            "DOMVALUE_H": "",
            "DOMVALUE_L": "30",
            "DOMVAL_HD": "",
            "DOMVAL_LD": "",
            "VALPOS": "0011"
        }
    ],
    "FV AUREL": [
        {
            "APPVAL": "",
            "DDLANGUAGE": "E",
            "DDTEXT": "Non-allocation-table-relevant",
            "DOMNAME": "AUREL",
            "DOMVALUE_H": "",
            "DOMVALUE_L": "",
            "DOMVAL_HD": "",
            "DOMVAL_LD": "",
            "VALPOS": "0001"
        },
        {
            "APPVAL": "",
            "DDLANGUAGE": "E",
            "DDTEXT": "Allocation-table-relevant: placement in storage",
            "DOMNAME": "AUREL",
            "DOMVALUE_H": "",
            "DOMVALUE_L": "1",
            "DOMVAL_HD": "",
            "DOMVAL_LD": "",
            "VALPOS": "0002"
        },
        {
            "APPVAL": "",
            "DDLANGUAGE": "E",
            "DDTEXT": "Allocation-table-relevant: cross-docking",
            "DOMNAME": "AUREL",
            "DOMVALUE_H": "",
            "DOMVALUE_L": "2",
            "DOMVAL_HD": "",
            "DOMVAL_LD": "",
            "VALPOS": "0003"
        },
        {
            "APPVAL": "",
            "DDLANGUAGE": "E",
            "DDTEXT": "Allocation-table-relevant: flow through",
            "DOMNAME": "AUREL",
            "DOMVALUE_H": "",
            "DOMVALUE_L": "3",
            "DOMVAL_HD": "",
            "DOMVAL_LD": "",
            "VALPOS": "0004"
        },
        {
            "APPVAL": "",
            "DDLANGUAGE": "E",
            "DDTEXT": "Allocation-table-relevant: cross docking/flow through",
            "DOMNAME": "AUREL",
            "DOMVALUE_H": "",
            "DOMVALUE_L": "4",
            "DOMVAL_HD": "",
            "DOMVAL_LD": "",
            "VALPOS": "0005"
        },
        {
            "APPVAL": "",
            "DDLANGUAGE": "E",
            "DDTEXT": "Alloc.-table-relevant: cross docking/placement in storage",
            "DOMNAME": "AUREL",
            "DOMVALUE_H": "",
            "DOMVALUE_L": "5",
            "DOMVAL_HD": "",
            "DOMVAL_LD": "",
            "VALPOS": "0006"
        }
    ],
    "FV BPUEB": [
        {
            "APPVAL": "",
            "DDLANGUAGE": "E",
            "DDTEXT": "Do not apply",
            "DOMNAME": "BPUEB",
            "DOMVALUE_H": "",
            "DOMVALUE_L": "",
            "DOMVAL_HD": "",
            "DOMVAL_LD": "",
            "VALPOS": "0001"
        },
        {
            "APPVAL": "",
            "DDLANGUAGE": "E",
            "DDTEXT": "As gross price",
            "DOMNAME": "BPUEB",
            "DOMVALUE_H": "",
            "DOMVALUE_L": "1",
            "DOMVAL_HD": "",
            "DOMVAL_LD": "",
            "VALPOS": "0002"
        },
        {
            "APPVAL": "",
            "DDLANGUAGE": "E",
            "DDTEXT": "As net price",
            "DOMNAME": "BPUEB",
            "DOMVALUE_H": "",
            "DOMVALUE_L": "2",
            "DOMVAL_HD": "",
            "DOMVAL_LD": "",
            "VALPOS": "0003"
        }
    ],
    "FV BSAKZ": [
        {
            "APPVAL": "",
            "DDLANGUAGE": "E",
            "DDTEXT": "Transport",
            "DOMNAME": "BSAKZ",
            "DOMVALUE_H": "",
            "DOMVALUE_L": "T",
            "DOMVAL_HD": "",
            "DOMVAL_LD": "",
            "VALPOS": "0001"
        },
        {
            "APPVAL": "",
            "DDLANGUAGE": "E",
            "DDTEXT": "Purchase requisition for outline agreement",
            "DOMNAME": "BSAKZ",
            "DOMVALUE_H": "",
            "DOMVALUE_L": "R",
            "DOMVAL_HD": "",
            "DOMVAL_LD": "",
            "VALPOS": "0002"
        }
    ],
    "FV BSTYP": [
        {
            "APPVAL": "",
            "DDLANGUAGE": "E",
            "DDTEXT": "Request for quotation",
            "DOMNAME": "BSTYP",
            "DOMVALUE_H": "",
            "DOMVALUE_L": "A",
            "DOMVAL_HD": "",
            "DOMVAL_LD": "",
            "VALPOS": "0001"
        },
        {
            "APPVAL": "",
            "DDLANGUAGE": "E",
            "DDTEXT": "Purchase requisition",
            "DOMNAME": "BSTYP",
            "DOMVALUE_H": "",
            "DOMVALUE_L": "B",
            "DOMVAL_HD": "",
            "DOMVAL_LD": "",
            "VALPOS": "0002"
        },
        {
            "APPVAL": "",
            "DDLANGUAGE": "E",
            "DDTEXT": "Purchase order",
            "DOMNAME": "BSTYP",
            "DOMVALUE_H": "",
            "DOMVALUE_L": "F",
            "DOMVAL_HD": "",
            "DOMVAL_LD": "",
            "VALPOS": "0003"
        },
        {
            "APPVAL": "",
            "DDLANGUAGE": "E",
            "DDTEXT": "Info record",
            "DOMNAME": "BSTYP",
            "DOMVALUE_H": "",
            "DOMVALUE_L": "I",
            "DOMVAL_HD": "",
            "DOMVAL_LD": "",
            "VALPOS": "0004"
        },
        {
            "APPVAL": "",
            "DDLANGUAGE": "E",
            "DDTEXT": "Contract",
            "DOMNAME": "BSTYP",
            "DOMVALUE_H": "",
            "DOMVALUE_L": "K",
            "DOMVAL_HD": "",
            "DOMVAL_LD": "",
            "VALPOS": "0005"
        },
        {
            "APPVAL": "",
            "DDLANGUAGE": "E",
            "DDTEXT": "Scheduling agreement",
            "DOMNAME": "BSTYP",
            "DOMVALUE_H": "",
            "DOMVALUE_L": "L",
            "DOMVAL_HD": "",
            "DOMVAL_LD": "",
            "VALPOS": "0006"
        },
        {
            "APPVAL": "",
            "DDLANGUAGE": "E",
            "DDTEXT": "Service entry sheet",
            "DOMNAME": "BSTYP",
            "DOMVALUE_H": "",
            "DOMVALUE_L": "Q",
            "DOMVAL_HD": "",
            "DOMVAL_LD": "",
            "VALPOS": "0007"
        },
        {
            "APPVAL": "",
            "DDLANGUAGE": "E",
            "DDTEXT": "Source list",
            "DOMNAME": "BSTYP",
            "DOMVALUE_H": "",
            "DOMVALUE_L": "W",
            "DOMVAL_HD": "",
            "DOMVAL_LD": "",
            "VALPOS": "0008"
        }
    ],
    "FV EBSTYP": [
        {
            "APPVAL": "",
            "DDLANGUAGE": "E",
            "DDTEXT": "Request for Quotation",
            "DOMNAME": "EBSTYP",
            "DOMVALUE_H": "",
            "DOMVALUE_L": "A",
            "DOMVAL_HD": "",
            "DOMVAL_LD": "",
            "VALPOS": "0001"
        },
        {
            "APPVAL": "",
            "DDLANGUAGE": "E",
            "DDTEXT": "Purchase Order",
            "DOMNAME": "EBSTYP",
            "DOMVALUE_H": "",
            "DOMVALUE_L": "F",
            "DOMVAL_HD": "",
            "DOMVAL_LD": "",
            "VALPOS": "0002"
        },
        {
            "APPVAL": "",
            "DDLANGUAGE": "E",
            "DDTEXT": "Contract",
            "DOMNAME": "EBSTYP",
            "DOMVALUE_H": "",
            "DOMVALUE_L": "K",
            "DOMVAL_HD": "",
            "DOMVAL_LD": "",
            "VALPOS": "0003"
        },
        {
            "APPVAL": "",
            "DDLANGUAGE": "E",
            "DDTEXT": "Scheduling Agreement",
            "DOMNAME": "EBSTYP",
            "DOMVALUE_H": "",
            "DOMVALUE_L": "L",
            "DOMVAL_HD": "",
            "DOMVAL_LD": "",
            "VALPOS": "0004"
        }
    ],
    "FV ESTAK": [
        {
            "APPVAL": "",
            "DDLANGUAGE": "E",
            "DDTEXT": "RFQ with Quotation",
            "DOMNAME": "ESTAK",
            "DOMVALUE_H": "",
            "DOMVALUE_L": "A",
            "DOMVAL_HD": "",
            "DOMVAL_LD": "",
            "VALPOS": "0001"
        },
        {
            "APPVAL": "",
            "DDLANGUAGE": "E",
            "DDTEXT": "Purchase Order from Automatic Conversion of Requisitions",
            "DOMNAME": "ESTAK",
            "DOMVALUE_H": "",
            "DOMVALUE_L": "B",
            "DOMVAL_HD": "",
            "DOMVAL_LD": "",
            "VALPOS": "0002"
        },
        {
            "APPVAL": "",
            "DDLANGUAGE": "E",
            "DDTEXT": "Purchase Order from Goods Receipt",
            "DOMNAME": "ESTAK",
            "DOMVALUE_H": "",
            "DOMVALUE_L": "C",
            "DOMVAL_HD": "",
            "DOMVAL_LD": "",
            "VALPOS": "0003"
        },
        {
            "APPVAL": "",
            "DDLANGUAGE": "E",
            "DDTEXT": "Purchase Order from Data Transfer",
            "DOMNAME": "ESTAK",
            "DOMVALUE_H": "",
            "DOMVALUE_L": "D",
            "DOMVAL_HD": "",
            "DOMVAL_LD": "",
            "VALPOS": "0004"
        },
        {
            "APPVAL": "",
            "DDLANGUAGE": "E",
            "DDTEXT": "Purchase Order from Allocation Table",
            "DOMNAME": "ESTAK",
            "DOMVALUE_H": "",
            "DOMVALUE_L": "E",
            "DOMVAL_HD": "",
            "DOMVAL_LD": "",
            "VALPOS": "0005"
        },
        {
            "APPVAL": "",
            "DDLANGUAGE": "E",
            "DDTEXT": "Purchase Order from Kanban",
            "DOMNAME": "ESTAK",
            "DOMVALUE_H": "",
            "DOMVALUE_L": "F",
            "DOMVAL_HD": "",
            "DOMVAL_LD": "",
            "VALPOS": "0006"
        },
        {
            "APPVAL": "",
            "DDLANGUAGE": "E",
            "DDTEXT": "Purchase Order from Store Order",
            "DOMNAME": "ESTAK",
            "DOMVALUE_H": "",
            "DOMVALUE_L": "G",
            "DOMVAL_HD": "",
            "DOMVAL_LD": "",
            "VALPOS": "0007"
        },
        {
            "APPVAL": "",
            "DDLANGUAGE": "E",
            "DDTEXT": "Purchase Order from DRP",
            "DOMNAME": "ESTAK",
            "DOMVALUE_H": "",
            "DOMVALUE_L": "H",
            "DOMVAL_HD": "",
            "DOMVAL_LD": "",
            "VALPOS": "0008"
        },
        {
            "APPVAL": "",
            "DDLANGUAGE": "E",
            "DDTEXT": "Purchase Order from BAPI",
            "DOMNAME": "ESTAK",
            "DOMVALUE_H": "",
            "DOMVALUE_L": "I",
            "DOMVAL_HD": "",
            "DOMVAL_LD": "",
            "VALPOS": "0009"
        },
        {
            "APPVAL": "",
            "DDLANGUAGE": "E",
            "DDTEXT": "Purchase Order from ALE Scenario",
            "DOMNAME": "ESTAK",
            "DOMVALUE_H": "",
            "DOMVALUE_L": "J",
            "DOMVAL_HD": "",
            "DOMVAL_LD": "",
            "VALPOS": "0010"
        },
        {
            "APPVAL": "",
            "DDLANGUAGE": "E",
            "DDTEXT": "Scheduling Agreement from CRM",
            "DOMNAME": "ESTAK",
            "DOMVALUE_H": "",
            "DOMVALUE_L": "L",
            "DOMVAL_HD": "",
            "DOMVAL_LD": "",
            "VALPOS": "0011"
        },
        {
            "APPVAL": "",
            "DDLANGUAGE": "E",
            "DDTEXT": "Collective Purchase Order",
            "DOMNAME": "ESTAK",
            "DOMVALUE_H": "",
            "DOMVALUE_L": "S",
            "DOMVAL_HD": "",
            "DOMVAL_LD": "",
            "VALPOS": "0012"
        },
        {
            "APPVAL": "",
            "DDLANGUAGE": "E",
            "DDTEXT": "Purchase Order Created via Function Module",
            "DOMNAME": "ESTAK",
            "DOMVALUE_H": "",
            "DOMVALUE_L": "X",
            "DOMVAL_HD": "",
            "DOMVAL_LD": "",
            "VALPOS": "0013"
        },
        {
            "APPVAL": "",
            "DDLANGUAGE": "E",
            "DDTEXT": "Purchase Order from APO",
            "DOMNAME": "ESTAK",
            "DOMVALUE_H": "",
            "DOMVALUE_L": "1",
            "DOMVAL_HD": "",
            "DOMVAL_LD": "",
            "VALPOS": "0014"
        },
        {
            "APPVAL": "",
            "DDLANGUAGE": "E",
            "DDTEXT": "Enjoy Purchase Order",
            "DOMNAME": "ESTAK",
            "DOMVALUE_H": "",
            "DOMVALUE_L": "9",
            "DOMVAL_HD": "",
            "DOMVAL_LD": "",
            "VALPOS": "0015"
        },
        {
            "APPVAL": "",
            "DDLANGUAGE": "E",
            "DDTEXT": "Purchase Order from BBP",
            "DOMNAME": "ESTAK",
            "DOMVALUE_H": "",
            "DOMVALUE_L": "K",
            "DOMVAL_HD": "",
            "DOMVAL_LD": "",
            "VALPOS": "0016"
        },
        {
            "APPVAL": "",
            "DDLANGUAGE": "E",
            "DDTEXT": "Third-Party Order from CRM",
            "DOMNAME": "ESTAK",
            "DOMVALUE_H": "",
            "DOMVALUE_L": "2",
            "DOMVAL_HD": "",
            "DOMVAL_LD": "",
            "VALPOS": "0017"
        },
        {
            "APPVAL": "",
            "DDLANGUAGE": "E",
            "DDTEXT": "Returns Order from Incorrect Delivery",
            "DOMNAME": "ESTAK",
            "DOMVALUE_H": "",
            "DOMVALUE_L": "3",
            "DOMVAL_HD": "",
            "DOMVAL_LD": "",
            "VALPOS": "0018"
        },
        {
            "APPVAL": "",
            "DDLANGUAGE": "E",
            "DDTEXT": "Purchasing Document from E-Sourcing",
            "DOMNAME": "ESTAK",
            "DOMVALUE_H": "",
            "DOMVALUE_L": "M",
            "DOMVAL_HD": "",
            "DOMVAL_LD": "",
            "VALPOS": "0019"
        },
        {
            "APPVAL": "",
            "DDLANGUAGE": "E",
            "DDTEXT": "Subsequent Stock Transport Order for Additional Item",
            "DOMNAME": "ESTAK",
            "DOMVALUE_H": "",
            "DOMVALUE_L": "4",
            "DOMVAL_HD": "",
            "DOMVAL_LD": "",
            "VALPOS": "0020"
        },
        {
            "APPVAL": "",
            "DDLANGUAGE": "E",
            "DDTEXT": "Incorrect Item Returns from Stock Transport Orders",
            "DOMNAME": "ESTAK",
            "DOMVALUE_H": "",
            "DOMVALUE_L": "5",
            "DOMVAL_HD": "",
            "DOMVAL_LD": "",
            "VALPOS": "0021"
        },
        {
            "APPVAL": "",
            "DDLANGUAGE": "E",
            "DDTEXT": "Purchase Order from Transportation Management",
            "DOMNAME": "ESTAK",
            "DOMVALUE_H": "",
            "DOMVALUE_L": "T",
            "DOMVAL_HD": "",
            "DOMVAL_LD": "",
            "VALPOS": "0022"
        }
    ],
    "FV ESTKZ": [
        {
            "APPVAL": "",
            "DDLANGUAGE": "E",
            "DDTEXT": "Material requirements planning",
            "DOMNAME": "ESTKZ",
            "DOMVALUE_H": "",
            "DOMVALUE_L": "B",
            "DOMVAL_HD": "",
            "DOMVAL_LD": "",
            "VALPOS": "0001"
        },
        {
            "APPVAL": "",
            "DDLANGUAGE": "E",
            "DDTEXT": "Direct procurement",
            "DOMNAME": "ESTKZ",
            "DOMVALUE_H": "",
            "DOMVALUE_L": "D",
            "DOMVAL_HD": "",
            "DOMVAL_LD": "",
            "VALPOS": "0002"
        },
        {
            "APPVAL": "",
            "DDLANGUAGE": "E",
            "DDTEXT": "Production order",
            "DOMNAME": "ESTKZ",
            "DOMVALUE_H": "",
            "DOMVALUE_L": "F",
            "DOMVAL_HD": "",
            "DOMVAL_LD": "",
            "VALPOS": "0003"
        },
        {
            "APPVAL": "",
            "DDLANGUAGE": "E",
            "DDTEXT": "Store order",
            "DOMNAME": "ESTKZ",
            "DOMVALUE_H": "",
            "DOMVALUE_L": "G",
            "DOMVAL_HD": "",
            "DOMVAL_LD": "",
            "VALPOS": "0004"
        },
        {
            "APPVAL": "",
            "DDLANGUAGE": "E",
            "DDTEXT": "Realtime (manual)",
            "DOMNAME": "ESTKZ",
            "DOMVALUE_H": "",
            "DOMVALUE_L": "R",
            "DOMVAL_HD": "",
            "DOMVAL_LD": "",
            "VALPOS": "0005"
        },
        {
            "APPVAL": "",
            "DDLANGUAGE": "E",
            "DDTEXT": "Converted planned order",
            "DOMNAME": "ESTKZ",
            "DOMVALUE_H": "",
            "DOMVALUE_L": "U",
            "DOMVAL_HD": "",
            "DOMVAL_LD": "",
            "VALPOS": "0006"
        },
        {
            "APPVAL": "",
            "DDLANGUAGE": "E",
            "DDTEXT": "Sales and distribution document",
            "DOMNAME": "ESTKZ",
            "DOMVALUE_H": "",
            "DOMVALUE_L": "V",
            "DOMVAL_HD": "",
            "DOMVAL_LD": "",
            "VALPOS": "0007"
        },
        {
            "APPVAL": "",
            "DDLANGUAGE": "E",
            "DDTEXT": "Compression (monthly basis)",
            "DOMNAME": "ESTKZ",
            "DOMVALUE_H": "",
            "DOMVALUE_L": "M",
            "DOMVAL_HD": "",
            "DOMVAL_LD": "",
            "VALPOS": "0008"
        },
        {
            "APPVAL": "",
            "DDLANGUAGE": "E",
            "DDTEXT": "Compression (annual basis)",
            "DOMNAME": "ESTKZ",
            "DOMVALUE_H": "",
            "DOMVALUE_L": "Y",
            "DOMVAL_HD": "",
            "DOMVAL_LD": "",
            "VALPOS": "0009"
        },
        {
            "APPVAL": "",
            "DDLANGUAGE": "E",
            "DDTEXT": "SAP APO",
            "DOMNAME": "ESTKZ",
            "DOMVALUE_H": "",
            "DOMVALUE_L": "A",
            "DOMVAL_HD": "",
            "DOMVAL_LD": "",
            "VALPOS": "0010"
        }
    ],
    "FV ETDRK": [
        {
            "APPVAL": "",
            "DDLANGUAGE": "E",
            "DDTEXT": "No print-relevant sch. agmt. schedules/lines from MRP",
            "DOMNAME": "ETDRK",
            "DOMVALUE_H": "",
            "DOMVALUE_L": "",
            "DOMVAL_HD": "",
            "DOMVAL_LD": "",
            "VALPOS": "0001"
        },
        {
            "APPVAL": "",
            "DDLANGUAGE": "E",
            "DDTEXT": "Print-relevant sch. agmt. schedules/lines from MRP",
            "DOMNAME": "ETDRK",
            "DOMVALUE_H": "",
            "DOMVALUE_L": "1",
            "DOMVAL_HD": "",
            "DOMVAL_LD": "",
            "VALPOS": "0002"
        },
        {
            "APPVAL": "",
            "DDLANGUAGE": "E",
            "DDTEXT": "Print-relevant sch. agmt. schedules/lines from dialog (ME38)",
            "DOMNAME": "ETDRK",
            "DOMVALUE_H": "",
            "DOMVALUE_L": "2",
            "DOMVAL_HD": "",
            "DOMVAL_LD": "",
            "VALPOS": "0003"
        },
        {
            "APPVAL": "",
            "DDLANGUAGE": "E",
            "DDTEXT": "Print-relevant change in services (SRV)",
            "DOMNAME": "ETDRK",
            "DOMVALUE_H": "",
            "DOMVALUE_L": "3",
            "DOMVAL_HD": "",
            "DOMVAL_LD": "",
            "VALPOS": "0004"
        }
    ],
    "FV FRGWF": [
        {
            "APPVAL": "",
            "DDLANGUAGE": "E",
            "DDTEXT": "No workflow",
            "DOMNAME": "FRGWF",
            "DOMVALUE_H": "",
            "DOMVALUE_L": "",
            "DOMVAL_HD": "",
            "DOMVAL_LD": "",
            "VALPOS": "0001"
        },
        {
            "APPVAL": "",
            "DDLANGUAGE": "E",
            "DDTEXT": "Role resolution with group, code, and plant (T16FW)",
            "DOMNAME": "FRGWF",
            "DOMVALUE_H": "",
            "DOMVALUE_L": "1",
            "DOMVAL_HD": "",
            "DOMVAL_LD": "",
            "VALPOS": "0002"
        },
        {
            "APPVAL": "",
            "DDLANGUAGE": "E",
            "DDTEXT": "Role resolution via user exit",
            "DOMNAME": "FRGWF",
            "DOMVALUE_H": "",
            "DOMVALUE_L": "9",
            "DOMVAL_HD": "",
            "DOMVAL_LD": "",
            "VALPOS": "0003"
        }
    ],
    "FV INSMK": [
        {
            "APPVAL": "",
            "DDLANGUAGE": "E",
            "DDTEXT": "Unrestricted use",
            "DOMNAME": "INSMK",
            "DOMVALUE_H": "",
            "DOMVALUE_L": "",
            "DOMVAL_HD": "",
            "DOMVAL_LD": "",
            "VALPOS": "0001"
        },
        {
            "APPVAL": "",
            "DDLANGUAGE": "E",
            "DDTEXT": "Quality inspection",
            "DOMNAME": "INSMK",
            "DOMVALUE_H": "",
            "DOMVALUE_L": "X",
            "DOMVAL_HD": "",
            "DOMVAL_LD": "",
            "VALPOS": "0002"
        },
        {
            "APPVAL": "",
            "DDLANGUAGE": "E",
            "DDTEXT": "Blocked stock",
            "DOMNAME": "INSMK",
            "DOMVALUE_H": "",
            "DOMVALUE_L": "S",
            "DOMVAL_HD": "",
            "DOMVAL_LD": "",
            "VALPOS": "0003"
        }
    ],
    "FV KBNKZ": [
        {
            "APPVAL": "",
            "DDLANGUAGE": "E",
            "DDTEXT": "Replenishment Element for Kanban",
            "DOMNAME": "KBNKZ",
            "DOMVALUE_H": "",
            "DOMVALUE_L": "X",
            "DOMVAL_HD": "",
            "DOMVAL_LD": "",
            "VALPOS": "0001"
        },
        {
            "APPVAL": "",
            "DDLANGUAGE": "E",
            "DDTEXT": "Scheduling Agreement for Summarized JIT Call",
            "DOMNAME": "KBNKZ",
            "DOMVALUE_H": "",
            "DOMVALUE_L": "Y",
            "DOMVAL_HD": "",
            "DOMVAL_LD": "",
            "VALPOS": "0002"
        }
    ],
    "FV KZCUH": [
        {
            "APPVAL": "",
            "DDLANGUAGE": "E",
            "DDTEXT": "External configuration",
            "DOMNAME": "KZCUH",
            "DOMVALUE_H": "",
            "DOMVALUE_L": "",
            "DOMVAL_HD": "",
            "DOMVAL_LD": "",
            "VALPOS": "0001"
        },
        {
            "APPVAL": "",
            "DDLANGUAGE": "E",
            "DDTEXT": "Configurable, but not yet configured",
            "DOMNAME": "KZCUH",
            "DOMVALUE_H": "",
            "DOMVALUE_L": "1",
            "DOMVAL_HD": "",
            "DOMVAL_LD": "",
            "VALPOS": "0002"
        },
        {
            "APPVAL": "",
            "DDLANGUAGE": "E",
            "DDTEXT": "Own configuration",
            "DOMNAME": "KZCUH",
            "DOMVALUE_H": "",
            "DOMVALUE_L": "2",
            "DOMVAL_HD": "",
            "DOMVAL_LD": "",
            "VALPOS": "0003"
        }
    ],
    "FV KZVBR": [
        {
            "APPVAL": "",
            "DDLANGUAGE": "E",
            "DDTEXT": "No consumption",
            "DOMNAME": "KZVBR",
            "DOMVALUE_H": "",
            "DOMVALUE_L": "",
            "DOMVAL_HD": "",
            "DOMVAL_LD": "",
            "VALPOS": "0001"
        },
        {
            "APPVAL": "",
            "DDLANGUAGE": "E",
            "DDTEXT": "Consumption",
            "DOMNAME": "KZVBR",
            "DOMVALUE_H": "",
            "DOMVALUE_L": "V",
            "DOMVAL_HD": "",
            "DOMVAL_LD": "",
            "VALPOS": "0002"
        },
        {
            "APPVAL": "",
            "DDLANGUAGE": "E",
            "DDTEXT": "Asset",
            "DOMNAME": "KZVBR",
            "DOMVALUE_H": "",
            "DOMVALUE_L": "A",
            "DOMVAL_HD": "",
            "DOMVAL_LD": "",
            "VALPOS": "0003"
        },
        {
            "APPVAL": "",
            "DDLANGUAGE": "E",
            "DDTEXT": "Sales order",
            "DOMNAME": "KZVBR",
            "DOMVALUE_H": "",
            "DOMVALUE_L": "E",
            "DOMVAL_HD": "",
            "DOMVAL_LD": "",
            "VALPOS": "0004"
        },
        {
            "APPVAL": "",
            "DDLANGUAGE": "E",
            "DDTEXT": "Project",
            "DOMNAME": "KZVBR",
            "DOMVALUE_H": "",
            "DOMVALUE_L": "P",
            "DOMVAL_HD": "",
            "DOMVAL_LD": "",
            "VALPOS": "0005"
        }
    ],
    "FV MEPRF": [
        {
            "APPVAL": "",
            "DDLANGUAGE": "E",
            "DDTEXT": "No Control",
            "DOMNAME": "MEPRF",
            "DOMVALUE_H": "",
            "DOMVALUE_L": "",
            "DOMVAL_HD": "",
            "DOMVAL_LD": "",
            "VALPOS": "0001"
        },
        {
            "APPVAL": "",
            "DDLANGUAGE": "E",
            "DDTEXT": "Purchase Order Date",
            "DOMNAME": "MEPRF",
            "DOMVALUE_H": "",
            "DOMVALUE_L": "1",
            "DOMVAL_HD": "",
            "DOMVAL_LD": "",
            "VALPOS": "0002"
        },
        {
            "APPVAL": "",
            "DDLANGUAGE": "E",
            "DDTEXT": "Delivery Date",
            "DOMNAME": "MEPRF",
            "DOMVALUE_H": "",
            "DOMVALUE_L": "2",
            "DOMVAL_HD": "",
            "DOMVAL_LD": "",
            "VALPOS": "0003"
        },
        {
            "APPVAL": "",
            "DDLANGUAGE": "E",
            "DDTEXT": "Current Date",
            "DOMNAME": "MEPRF",
            "DOMVALUE_H": "",
            "DOMVALUE_L": "3",
            "DOMVAL_HD": "",
            "DOMVAL_LD": "",
            "VALPOS": "0004"
        },
        {
            "APPVAL": "",
            "DDLANGUAGE": "E",
            "DDTEXT": "Manual",
            "DOMNAME": "MEPRF",
            "DOMVALUE_H": "",
            "DOMVALUE_L": "4",
            "DOMVAL_HD": "",
            "DOMVAL_LD": "",
            "VALPOS": "0005"
        },
        {
            "APPVAL": "",
            "DDLANGUAGE": "E",
            "DDTEXT": "GR Date",
            "DOMNAME": "MEPRF",
            "DOMVALUE_H": "",
            "DOMVALUE_L": "5",
            "DOMVAL_HD": "",
            "DOMVAL_LD": "",
            "VALPOS": "0006"
        }
    ],
    "FV OBJ_TO_GEN": [
        {
            "APPVAL": "",
            "DDLANGUAGE": "E",
            "DDTEXT": "Reservation",
            "DOMNAME": "OBJ_TO_GEN",
            "DOMVALUE_H": "",
            "DOMVALUE_L": "1",
            "DOMVAL_HD": "",
            "DOMVAL_LD": "",
            "VALPOS": "0001"
        },
        {
            "APPVAL": "",
            "DDLANGUAGE": "E",
            "DDTEXT": "Purchase requisition",
            "DOMNAME": "OBJ_TO_GEN",
            "DOMVALUE_H": "",
            "DOMVALUE_L": "2",
            "DOMVAL_HD": "",
            "DOMVAL_LD": "",
            "VALPOS": "0002"
        },
        {
            "APPVAL": "",
            "DDLANGUAGE": "E",
            "DDTEXT": "Purchase order",
            "DOMNAME": "OBJ_TO_GEN",
            "DOMVALUE_H": "",
            "DOMVALUE_L": "3",
            "DOMVAL_HD": "",
            "DOMVAL_LD": "",
            "VALPOS": "0003"
        },
        {
            "APPVAL": "",
            "DDLANGUAGE": "E",
            "DDTEXT": "Other usage for customer",
            "DOMNAME": "OBJ_TO_GEN",
            "DOMVALUE_H": "",
            "DOMVALUE_L": "4",
            "DOMVAL_HD": "",
            "DOMVAL_LD": "",
            "VALPOS": "0004"
        },
        {
            "APPVAL": "",
            "DDLANGUAGE": "E",
            "DDTEXT": "Reserved",
            "DOMNAME": "OBJ_TO_GEN",
            "DOMVALUE_H": "",
            "DOMVALUE_L": "5",
            "DOMVAL_HD": "",
            "DOMVAL_LD": "",
            "VALPOS": "0005"
        },
        {
            "APPVAL": "",
            "DDLANGUAGE": "E",
            "DDTEXT": "Reserved",
            "DOMNAME": "OBJ_TO_GEN",
            "DOMVALUE_H": "",
            "DOMVALUE_L": "6",
            "DOMVAL_HD": "",
            "DOMVAL_LD": "",
            "VALPOS": "0006"
        },
        {
            "APPVAL": "",
            "DDLANGUAGE": "E",
            "DDTEXT": "Reserved",
            "DOMNAME": "OBJ_TO_GEN",
            "DOMVALUE_H": "",
            "DOMVALUE_L": "7",
            "DOMVAL_HD": "",
            "DOMVAL_LD": "",
            "VALPOS": "0007"
        },
        {
            "APPVAL": "",
            "DDLANGUAGE": "E",
            "DDTEXT": "Reserved",
            "DOMNAME": "OBJ_TO_GEN",
            "DOMVALUE_H": "",
            "DOMVALUE_L": "8",
            "DOMVAL_HD": "",
            "DOMVAL_LD": "",
            "VALPOS": "0008"
        },
        {
            "APPVAL": "",
            "DDLANGUAGE": "E",
            "DDTEXT": "Reserved",
            "DOMNAME": "OBJ_TO_GEN",
            "DOMVALUE_H": "",
            "DOMVALUE_L": "9",
            "DOMVAL_HD": "",
            "DOMVAL_LD": "",
            "VALPOS": "0009"
        }
    ],
    "FV PRGRS": [
        {
            "APPVAL": "",
            "DDLANGUAGE": "E",
            "DDTEXT": "Day",
            "DOMNAME": "PRGRS",
            "DOMVALUE_H": "",
            "DOMVALUE_L": "1",
            "DOMVAL_HD": "",
            "DOMVAL_LD": "",
            "VALPOS": "0001"
        },
        {
            "APPVAL": "",
            "DDLANGUAGE": "E",
            "DDTEXT": "Week",
            "DOMNAME": "PRGRS",
            "DOMVALUE_H": "",
            "DOMVALUE_L": "2",
            "DOMVAL_HD": "",
            "DOMVAL_LD": "",
            "VALPOS": "0002"
        },
        {
            "APPVAL": "",
            "DDLANGUAGE": "E",
            "DDTEXT": "Month",
            "DOMNAME": "PRGRS",
            "DOMVALUE_H": "",
            "DOMVALUE_L": "3",
            "DOMVAL_HD": "",
            "DOMVAL_LD": "",
            "VALPOS": "0003"
        },
        {
            "APPVAL": "",
            "DDLANGUAGE": "E",
            "DDTEXT": "Posting period",
            "DOMNAME": "PRGRS",
            "DOMVALUE_H": "",
            "DOMVALUE_L": "4",
            "DOMVAL_HD": "",
            "DOMVAL_LD": "",
            "VALPOS": "0004"
        },
        {
            "APPVAL": "",
            "DDLANGUAGE": "E",
            "DDTEXT": "Planning calendar period",
            "DOMNAME": "PRGRS",
            "DOMVALUE_H": "",
            "DOMVALUE_L": "5",
            "DOMVAL_HD": "",
            "DOMVAL_LD": "",
            "VALPOS": "0005"
        }
    ],
    "FV SELKZ": [
        {
            "APPVAL": "",
            "DDLANGUAGE": "E",
            "DDTEXT": "Not selected",
            "DOMNAME": "SELKZ",
            "DOMVALUE_H": "",
            "DOMVALUE_L": "",
            "DOMVAL_HD": "",
            "DOMVAL_LD": "",
            "VALPOS": "0001"
        },
        {
            "APPVAL": "",
            "DDLANGUAGE": "E",
            "DDTEXT": "Selected and processed",
            "DOMNAME": "SELKZ",
            "DOMVALUE_H": "",
            "DOMVALUE_L": "*",
            "DOMVAL_HD": "",
            "DOMVAL_LD": "",
            "VALPOS": "0002"
        },
        {
            "APPVAL": "",
            "DDLANGUAGE": "E",
            "DDTEXT": "Selected but not yet processed",
            "DOMNAME": "SELKZ",
            "DOMVALUE_H": "",
            "DOMVALUE_L": "X",
            "DOMVAL_HD": "",
            "DOMVAL_LD": "",
            "VALPOS": "0003"
        }
    ],
    "FV SHKZG": [
        {
            "APPVAL": "",
            "DDLANGUAGE": "E",
            "DDTEXT": "Credit",
            "DOMNAME": "SHKZG",
            "DOMVALUE_H": "",
            "DOMVALUE_L": "H",
            "DOMVAL_HD": "",
            "DOMVAL_LD": "",
            "VALPOS": "0001"
        },
        {
            "APPVAL": "",
            "DDLANGUAGE": "E",
            "DDTEXT": "Debit",
            "DOMNAME": "SHKZG",
            "DOMVALUE_H": "",
            "DOMVALUE_L": "S",
            "DOMVAL_HD": "",
            "DOMVAL_LD": "",
            "VALPOS": "0002"
        }
    ],
    "FV SPINF": [
        {
            "APPVAL": "",
            "DDLANGUAGE": "E",
            "DDTEXT": "No update",
            "DOMNAME": "SPINF",
            "DOMVALUE_H": "",
            "DOMVALUE_L": "",
            "DOMVAL_HD": "",
            "DOMVAL_LD": "",
            "VALPOS": "0001"
        },
        {
            "APPVAL": "",
            "DDLANGUAGE": "E",
            "DDTEXT": "Update with or without plant",
            "DOMNAME": "SPINF",
            "DOMVALUE_H": "",
            "DOMVALUE_L": "A",
            "DOMVAL_HD": "",
            "DOMVAL_LD": "",
            "VALPOS": "0002"
        },
        {
            "APPVAL": "",
            "DDLANGUAGE": "E",
            "DDTEXT": "Update with plant (if no plant ban)",
            "DOMNAME": "SPINF",
            "DOMVALUE_H": "",
            "DOMVALUE_L": "B",
            "DOMVAL_HD": "",
            "DOMVAL_LD": "",
            "VALPOS": "0003"
        },
        {
            "APPVAL": "",
            "DDLANGUAGE": "E",
            "DDTEXT": "Update without plant (if no plant requirement)",
            "DOMNAME": "SPINF",
            "DOMVALUE_H": "",
            "DOMVALUE_L": "C",
            "DOMVAL_HD": "",
            "DOMVAL_LD": "",
            "VALPOS": "0004"
        }
    ],
    "FV TWRKZ": [
        {
            "APPVAL": "",
            "DDLANGUAGE": "E",
            "DDTEXT": "No multiple account assignment",
            "DOMNAME": "TWRKZ",
            "DOMVALUE_H": "",
            "DOMVALUE_L": "",
            "DOMVAL_HD": "",
            "DOMVAL_LD": "",
            "VALPOS": "0001"
        },
        {
            "APPVAL": "",
            "DDLANGUAGE": "E",
            "DDTEXT": "Apportion IR quantities to GR quantities one after another",
            "DOMNAME": "TWRKZ",
            "DOMVALUE_H": "",
            "DOMVALUE_L": "1",
            "DOMVAL_HD": "",
            "DOMVAL_LD": "",
            "VALPOS": "0002"
        },
        {
            "APPVAL": "",
            "DDLANGUAGE": "E",
            "DDTEXT": "Apportion IR quantities to GR quantities proportionately",
            "DOMNAME": "TWRKZ",
            "DOMVALUE_H": "",
            "DOMVALUE_L": "2",
            "DOMVAL_HD": "",
            "DOMVAL_LD": "",
            "VALPOS": "0003"
        }
    ],
    "FV VGABE": [
        {
            "APPVAL": "",
            "DDLANGUAGE": "E",
            "DDTEXT": "Goods Receipt",
            "DOMNAME": "VGABE",
            "DOMVALUE_H": "",
            "DOMVALUE_L": "1",
            "DOMVAL_HD": "",
            "DOMVAL_LD": "",
            "VALPOS": "0001"
        },
        {
            "APPVAL": "",
            "DDLANGUAGE": "E",
            "DDTEXT": "Invoice Receipt",
            "DOMNAME": "VGABE",
            "DOMVALUE_H": "",
            "DOMVALUE_L": "2",
            "DOMVAL_HD": "",
            "DOMVAL_LD": "",
            "VALPOS": "0002"
        },
        {
            "APPVAL": "",
            "DDLANGUAGE": "E",
            "DDTEXT": "Subseq. Debit/Credit",
            "DOMNAME": "VGABE",
            "DOMVALUE_H": "",
            "DOMVALUE_L": "3",
            "DOMVAL_HD": "",
            "DOMVAL_LD": "",
            "VALPOS": "0003"
        },
        {
            "APPVAL": "",
            "DDLANGUAGE": "E",
            "DDTEXT": "Down Payment",
            "DOMNAME": "VGABE",
            "DOMVALUE_H": "",
            "DOMVALUE_L": "4",
            "DOMVAL_HD": "",
            "DOMVAL_LD": "",
            "VALPOS": "0004"
        },
        {
            "APPVAL": "",
            "DDLANGUAGE": "E",
            "DDTEXT": "Payment",
            "DOMNAME": "VGABE",
            "DOMVALUE_H": "",
            "DOMVALUE_L": "5",
            "DOMVAL_HD": "",
            "DOMVAL_LD": "",
            "VALPOS": "0005"
        },
        {
            "APPVAL": "",
            "DDLANGUAGE": "E",
            "DDTEXT": "Goods Issue for Stock Transfer",
            "DOMNAME": "VGABE",
            "DOMVALUE_H": "",
            "DOMVALUE_L": "6",
            "DOMVAL_HD": "",
            "DOMVAL_LD": "",
            "VALPOS": "0006"
        },
        {
            "APPVAL": "",
            "DDLANGUAGE": "E",
            "DDTEXT": "Consumption (Subcontracting)",
            "DOMNAME": "VGABE",
            "DOMVALUE_H": "",
            "DOMVALUE_L": "7",
            "DOMVAL_HD": "",
            "DOMVAL_LD": "",
            "VALPOS": "0007"
        },
        {
            "APPVAL": "",
            "DDLANGUAGE": "E",
            "DDTEXT": "Delivery (Stock Transfer)",
            "DOMNAME": "VGABE",
            "DOMVALUE_H": "",
            "DOMVALUE_L": "8",
            "DOMVAL_HD": "",
            "DOMVAL_LD": "",
            "VALPOS": "0008"
        },
        {
            "APPVAL": "",
            "DDLANGUAGE": "E",
            "DDTEXT": "Service Entry Sheet",
            "DOMNAME": "VGABE",
            "DOMVALUE_H": "",
            "DOMVALUE_L": "9",
            "DOMVAL_HD": "",
            "DOMVAL_LD": "",
            "VALPOS": "0009"
        },
        {
            "APPVAL": "",
            "DDLANGUAGE": "E",
            "DDTEXT": "Down Payment Request",
            "DOMNAME": "VGABE",
            "DOMVALUE_H": "",
            "DOMVALUE_L": "A",
            "DOMVAL_HD": "",
            "DOMVAL_LD": "",
            "VALPOS": "0010"
        },
        {
            "APPVAL": "",
            "DDLANGUAGE": "E",
            "DDTEXT": "Down Payment Clearing",
            "DOMNAME": "VGABE",
            "DOMVALUE_H": "",
            "DOMVALUE_L": "C",
            "DOMVAL_HD": "",
            "DOMVAL_LD": "",
            "VALPOS": "0011"
        },
        {
            "APPVAL": "",
            "DDLANGUAGE": "E",
            "DDTEXT": "Comparison for Internally Posted Material (Only IS-OIL)",
            "DOMNAME": "VGABE",
            "DOMVALUE_H": "",
            "DOMVALUE_L": "Q",
            "DOMVAL_HD": "",
            "DOMVAL_LD": "",
            "VALPOS": "0012"
        },
        {
            "APPVAL": "",
            "DDLANGUAGE": "E",
            "DDTEXT": "Return Delivery via Delivery Note",
            "DOMNAME": "VGABE",
            "DOMVALUE_H": "",
            "DOMVALUE_L": "R",
            "DOMVAL_HD": "",
            "DOMVAL_LD": "",
            "VALPOS": "0013"
        },
        {
            "APPVAL": "",
            "DDLANGUAGE": "E",
            "DDTEXT": "Invoice Parking",
            "DOMNAME": "VGABE",
            "DOMVALUE_H": "",
            "DOMVALUE_L": "P",
            "DOMVAL_HD": "",
            "DOMVAL_LD": "",
            "VALPOS": "0014"
        },
        {
            "APPVAL": "",
            "DDLANGUAGE": "E",
            "DDTEXT": "Down Payment Request Clearing",
            "DOMNAME": "VGABE",
            "DOMVALUE_H": "",
            "DOMVALUE_L": "V",
            "DOMVAL_HD": "",
            "DOMVAL_LD": "",
            "VALPOS": "0015"
        },
        {
            "APPVAL": "X",
            "DDLANGUAGE": "E",
            "DDTEXT": "Posted Subsequent Debit with Reference to a Contract",
            "DOMNAME": "VGABE",
            "DOMVALUE_H": "",
            "DOMVALUE_L": "M",
            "DOMVAL_HD": "",
            "DOMVAL_LD": "",
            "VALPOS": "0016"
        },
        {
            "APPVAL": "X",
            "DDLANGUAGE": "E",
            "DDTEXT": "Posted Invoice with Reference to a Contract",
            "DOMNAME": "VGABE",
            "DOMVALUE_H": "",
            "DOMVALUE_L": "K",
            "DOMVAL_HD": "",
            "DOMVAL_LD": "",
            "VALPOS": "0017"
        },
        {
            "APPVAL": "X",
            "DDLANGUAGE": "E",
            "DDTEXT": "Parked Invoice with Reference to a Contract",
            "DOMNAME": "VGABE",
            "DOMVALUE_H": "",
            "DOMVALUE_L": "L",
            "DOMVAL_HD": "",
            "DOMVAL_LD": "",
            "VALPOS": "0018"
        },
        {
            "APPVAL": "X",
            "DDLANGUAGE": "E",
            "DDTEXT": "Posted Subsequent Debit for Contract in Blanket PO",
            "DOMNAME": "VGABE",
            "DOMVALUE_H": "",
            "DOMVALUE_L": "N",
            "DOMVAL_HD": "",
            "DOMVAL_LD": "",
            "VALPOS": "0019"
        },
        {
            "APPVAL": "X",
            "DDLANGUAGE": "E",
            "DDTEXT": "Posted Invoice for Contract in Blanket Purchase Order",
            "DOMNAME": "VGABE",
            "DOMVALUE_H": "",
            "DOMVALUE_L": "O",
            "DOMVAL_HD": "",
            "DOMVAL_LD": "",
            "VALPOS": "0020"
        },
        {
            "APPVAL": "X",
            "DDLANGUAGE": "E",
            "DDTEXT": "Parked Invoice for Contract in Blanket Purchase Order",
            "DOMNAME": "VGABE",
            "DOMVALUE_H": "",
            "DOMVALUE_L": "G",
            "DOMVAL_HD": "",
            "DOMVAL_LD": "",
            "VALPOS": "0021"
        }
    ],
    "FV VRTKZ": [
        {
            "APPVAL": "",
            "DDLANGUAGE": "E",
            "DDTEXT": "Single account assignment",
            "DOMNAME": "VRTKZ",
            "DOMVALUE_H": "",
            "DOMVALUE_L": "",
            "DOMVAL_HD": "",
            "DOMVAL_LD": "",
            "VALPOS": "0001"
        },
        {
            "APPVAL": "",
            "DDLANGUAGE": "E",
            "DDTEXT": "Distrib. on quantity basis",
            "DOMNAME": "VRTKZ",
            "DOMVALUE_H": "",
            "DOMVALUE_L": "1",
            "DOMVAL_HD": "",
            "DOMVAL_LD": "",
            "VALPOS": "0002"
        },
        {
            "APPVAL": "",
            "DDLANGUAGE": "E",
            "DDTEXT": "Distribution by percentage",
            "DOMNAME": "VRTKZ",
            "DOMVALUE_H": "",
            "DOMVALUE_L": "2",
            "DOMVAL_HD": "",
            "DOMVAL_LD": "",
            "VALPOS": "0003"
        }
    ],
    "SH ASMD": null,
    "SH CITYA": null,
    "SH CITY_NAME": null,
    "SH CITY_PART": null,
    "SH CLCITYNAME": null,
    "SH CLSTRTNAME": null,
    "SH CPRTA": null,
    "SH CSH_TKA01": null,
    "SH C_SAKNR": null,
    "SH C_T001": null,
    "SH DEBI": null,
    "SH F4_INTCA": null,
    "SH GRANTS_GENERIC": null,
    "SH H_MKAL": null,
    "SH H_SNUM": null,
    "SH H_T001L": null,
    "SH H_T001W": null,
    "SH H_T002": null,
    "SH H_T006": null,
    "SH H_T006I": null,
    "SH H_T023": null,
    "SH H_T024": null,
    "SH H_T024E": null,
    "SH H_T027A": null,
    "SH H_T134": null,
    "SH H_T148": null,
    "SH H_T149C": null,
    "SH H_T149D": null,
    "SH H_T156": null,
    "SH H_T157D": null,
    "SH H_T161": null,
    "SH H_T163": null,
    "SH H_T163B": null,
    "SH H_T163K": null,
    "SH H_T604": null,
    "SH H_T605": null,
    "SH H_T8JJ": null,
    "SH H_TGSB": null,
    "SH H_TINC": null,
    "SH H_TMCB": null,
    "SH H_TMQ2": null,
    "SH H_TPRG": null,
    "SH H_TQ05": null,
    "SH H_TQ08": null,
    "SH H_TTXJ": null,
    "SH H_TVLK": null,
    "SH KRED": null,
    "SH MBAN_C": null,
    "SH MEKK_C": null,
    "SH PD_C": null,
    "SH PRCTR_EMPTY": null,
    "SH SAKO": null,
    "SH SGT_CAT_FIELD_POPUP": null,
    "SH SPEC": null,
    "SH SSH_T007A": null,
    "SH STRTA": null,
    "SH VTTZZ": null
}